baekjoon/args.py
baekjoon/boj.py
baekjoon/problem.py
baekjoon/solvedac.py
baekjoon_scraper-1.0.2.dist-info/METADATA
baekjoon_scraper-1.0.2.dist-info/WHEEL
baekjoon_scraper-1.0.2.dist-info/top_level.txt
baekjoon_scraper-1.0.2.dist-info/RECORD
