Metadata-Version: 2.1
Name: baekjoon-scraper
Version: 1.0.2
Summary: A fork of smartwe's baekjoon api with optional argument fields for avoiding scraping detection
Home-page: https://github.com/RoelYoon/baekjoon-scraper-api.git
Author: RoelYoon
Author-email: roelyoon2@gmail.com
License: MIT
Requires-Python: >=3
Requires-Dist: bs4
Requires-Dist: requests
